README.rst
django_micro.py
setup.py
django_micro.egg-info/PKG-INFO
django_micro.egg-info/SOURCES.txt
django_micro.egg-info/dependency_links.txt
django_micro.egg-info/requires.txt
django_micro.egg-info/top_level.txt