Metadata-Version: 1.1
Name: django-micro
Version: 1.5
Summary: Django as a microframework
Home-page: https://github.com/zenwalker/django-micro
Author: Max Poletaev
Author-email: max.poletaev@gmail.com
License: BSD
Keywords: django microframework
Platform: UNKNOWN
Classifier: Programming Language :: Python
Classifier: Programming Language :: Python :: 3.4
Classifier: Programming Language :: Python :: 3.5
Classifier: Programming Language :: Python :: 3.6
Classifier: Framework :: Django
Classifier: Framework :: Django :: 2.0
